voter_tools/__init__.py
voter_tools/cli.py
voter_tools/errors.py
voter_tools/ga.py
voter_tools/mi.py
voter_tools/soup_utils.py
voter_tools/tool.py
voter_tools/wi.py
voter_tools/zipcodes.py
voter_tools/zipcodes.us.csv
voter_tools/pa/__init__.py
voter_tools/pa/address.py
voter_tools/pa/check.py
voter_tools/pa/client.py
voter_tools/pa/counties.py
voter_tools/pa/debug.py
voter_tools/pa/errors.py
voter_tools-0.0.23.dist-info/licenses/LICENSE
voter_tools-0.0.23.dist-info/METADATA
voter_tools-0.0.23.dist-info/WHEEL
voter_tools-0.0.23.dist-info/entry_points.txt
voter_tools-0.0.23.dist-info/top_level.txt
voter_tools-0.0.23.dist-info/RECORD
