Metadata-Version: 2.4
Name: voter-tools
Version: 0.0.23
Summary: Tools for online voter registration in the United States of America
Author-email: Dave Peck <dave@frontseat.org>
License: MIT
Project-URL: Homepage, https://github.com/front-seat/voter-tools
Project-URL: Changelog, https://github.com/front-seat/voter-tools/releases
Project-URL: Issues, https://github.com/front-seat/voter-tools/issues
Project-URL: CI, https://github.com/front-seat/voter-tools/actions
Classifier: License :: OSI Approved :: MIT License
Classifier: Programming Language :: Python :: 3 :: Only
Classifier: Programming Language :: Python :: 3.12
Classifier: Programming Language :: Python :: 3.13
Requires-Python: >=3.12
License-File: LICENSE
Requires-Dist: beautifulsoup4>=4.13.4
Requires-Dist: click>=8.1.8
Requires-Dist: httpx>=0.28.1
Requires-Dist: pillow>=11.2.1
Requires-Dist: pydantic-xml>=2.16.0
Requires-Dist: pydantic[email]>=2.11.4
Requires-Dist: user-agent>=0.1.10
Provides-Extra: dev
Requires-Dist: ruff; extra == "dev"
Requires-Dist: mypy; extra == "dev"
Provides-Extra: build
Requires-Dist: setuptools; extra == "build"
Requires-Dist: wheel; extra == "build"
Requires-Dist: build; extra == "build"
Provides-Extra: lxml
Requires-Dist: lxml; extra == "lxml"
Dynamic: license-file
